SanketYoHiPie/__init__.py
SanketYoHiPie-0.3.dist-info/METADATA
SanketYoHiPie-0.3.dist-info/WHEEL
SanketYoHiPie-0.3.dist-info/top_level.txt
SanketYoHiPie-0.3.dist-info/RECORD
