Metadata-Version: 2.1
Name: SanketYoHiPie
Version: 0.3
Summary: A simple Python library for handling STT functionality
Author: Sanket3yoprogrammer
Author-email: sanket@example.com
